werkzeug/__init__.py
werkzeug/_compat.py
werkzeug/_internal.py
werkzeug/_reloader.py
werkzeug/datastructures.py
werkzeug/exceptions.py
werkzeug/filesystem.py
werkzeug/formparser.py
werkzeug/http.py
werkzeug/local.py
werkzeug/posixemulation.py
werkzeug/routing.py
werkzeug/security.py
werkzeug/serving.py
werkzeug/test.py
werkzeug/testapp.py
werkzeug/urls.py
werkzeug/useragents.py
werkzeug/utils.py
werkzeug/wsgi.py
werkzeug/debug/__init__.py
werkzeug/debug/console.py
werkzeug/debug/repr.py
werkzeug/debug/tbtools.py
werkzeug/debug/shared/FONT_LICENSE
werkzeug/debug/shared/console.png
werkzeug/debug/shared/debugger.js
werkzeug/debug/shared/jquery.js
werkzeug/debug/shared/less.png
werkzeug/debug/shared/more.png
werkzeug/debug/shared/source.png
werkzeug/debug/shared/style.css
werkzeug/debug/shared/ubuntu.ttf
werkzeug/middleware/__init__.py
werkzeug/middleware/dispatcher.py
werkzeug/middleware/http_proxy.py
werkzeug/middleware/lint.py
werkzeug/middleware/profiler.py
werkzeug/middleware/proxy_fix.py
werkzeug/middleware/shared_data.py
werkzeug/wrappers/__init__.py
werkzeug/wrappers/accept.py
werkzeug/wrappers/auth.py
werkzeug/wrappers/base_request.py
werkzeug/wrappers/base_response.py
werkzeug/wrappers/common_descriptors.py
werkzeug/wrappers/cors.py
werkzeug/wrappers/etag.py
werkzeug/wrappers/json.py
werkzeug/wrappers/request.py
werkzeug/wrappers/response.py
werkzeug/wrappers/user_agent.py
Werkzeug-1.0.0.dist-info/LICENSE.rst
Werkzeug-1.0.0.dist-info/METADATA
Werkzeug-1.0.0.dist-info/WHEEL
Werkzeug-1.0.0.dist-info/top_level.txt
Werkzeug-1.0.0.dist-info/RECORD
